AUTHORS
LICENSE
MANIFEST.in
README.md
setup.py
django_zen/__init__.py
django_zen/admin.py
django_zen/models.py
django_zen/tests.py
django_zen/urls.py
django_zen/views.py
django_zen.egg-info/PKG-INFO
django_zen.egg-info/SOURCES.txt
django_zen.egg-info/dependency_links.txt
django_zen.egg-info/not-zip-safe
django_zen.egg-info/requires.txt
django_zen.egg-info/top_level.txt
django_zen/locale/ru/LC_MESSAGES/django.mo
django_zen/locale/ru/LC_MESSAGES/django.po
django_zen/templatetags/__init__.py
django_zen/templatetags/menu_tags.py