Metadata-Version: 1.1
Name: django-zen
Version: 0.1.8
Summary: Zen-Lightweight Django CMS
Home-page: https://github.com/DigitalDemiurge/django-zen.git
Author: Vitaliy Korobkin
Author-email: root@digitaldemiurge.me
License: MIT license
Platform: UNKNOWN
Classifier: Topic :: Internet :: WWW/HTTP :: Dynamic Content
Classifier: Intended Audience :: Developers
Classifier: Programming Language :: Python
Classifier: Programming Language :: Python :: 2.6
Classifier: Programming Language :: Python :: 2.7
Classifier: Framework :: Django
Classifier: Development Status :: 4 - Beta
Classifier: Operating System :: OS Independent
